README.md
setup.py
./pytpp/__init__.py
./pytpp/_about.py
./pytpp/api/__init__.py
./pytpp/api/api_base.py
./pytpp/api/authenticate.py
./pytpp/api/session.py
./pytpp/api/websdk/__init__.py
./pytpp/api/websdk/websdk.py
./pytpp/api/websdk/endpoints/__init__.py
./pytpp/api/websdk/endpoints/authorize.py
./pytpp/api/websdk/endpoints/certificates.py
./pytpp/api/websdk/endpoints/client.py
./pytpp/api/websdk/endpoints/codesign.py
./pytpp/api/websdk/endpoints/config.py
./pytpp/api/websdk/endpoints/config_schema.py
./pytpp/api/websdk/endpoints/credentials.py
./pytpp/api/websdk/endpoints/crypto.py
./pytpp/api/websdk/endpoints/discovery.py
./pytpp/api/websdk/endpoints/flow.py
./pytpp/api/websdk/endpoints/hsm_api.py
./pytpp/api/websdk/endpoints/identity.py
./pytpp/api/websdk/endpoints/log.py
./pytpp/api/websdk/endpoints/metadata.py
./pytpp/api/websdk/endpoints/permissions.py
./pytpp/api/websdk/endpoints/pki.py
./pytpp/api/websdk/endpoints/platform.py
./pytpp/api/websdk/endpoints/preferences.py
./pytpp/api/websdk/endpoints/processing_engines.py
./pytpp/api/websdk/endpoints/recycle_bin.py
./pytpp/api/websdk/endpoints/revoke.py
./pytpp/api/websdk/endpoints/secret_store.py
./pytpp/api/websdk/endpoints/ssh.py
./pytpp/api/websdk/endpoints/ssh_certificates.py
./pytpp/api/websdk/endpoints/stats.py
./pytpp/api/websdk/endpoints/system_status.py
./pytpp/api/websdk/endpoints/teams.py
./pytpp/api/websdk/endpoints/workflow.py
./pytpp/api/websdk/endpoints/x509_certificate_store.py
./pytpp/api/websdk/enums/__init__.py
./pytpp/api/websdk/enums/certificate.py
./pytpp/api/websdk/enums/codesign.py
./pytpp/api/websdk/enums/config.py
./pytpp/api/websdk/enums/config_schema.py
./pytpp/api/websdk/enums/metadata.py
./pytpp/api/websdk/enums/oauth.py
./pytpp/api/websdk/enums/permissions.py
./pytpp/api/websdk/enums/rights.py
./pytpp/api/websdk/enums/secret_store.py
./pytpp/api/websdk/enums/ssh.py
./pytpp/api/websdk/models/__init__.py
./pytpp/api/websdk/models/certificate.py
pytpp.egg-info/PKG-INFO
pytpp.egg-info/SOURCES.txt
pytpp.egg-info/dependency_links.txt
pytpp.egg-info/requires.txt
pytpp.egg-info/top_level.txt