Metadata-Version: 2.1
Name: pytpp
Version: 2.0.3
Summary: Venafi TPP Features and WebSDK API In Python
Home-page: https://github.com/Venafi/pytpp
Author: Venafi SPI Team
Author-email: spi@venafi.com
License: UNKNOWN
Keywords: pytpp,venafi,tpp,trust protection platform
Platform: UNKNOWN
Classifier: Development Status :: 4 - Beta
Classifier: Intended Audience :: Developers
Classifier: License :: OSI Approved :: MIT License
Classifier: Natural Language :: English
Classifier: Programming Language :: Python :: 3.8
Classifier: Topic :: Software Development :: Libraries :: Python Modules
Provides-Extra: doc
Provides-Extra: all
Provides-Extra: dev
